arbitrage_tools/__init__.py
arbitrage_tools-0.1.0.dist-info/licenses/LICENSE
arbitrage_tools-0.1.0.dist-info/METADATA
arbitrage_tools-0.1.0.dist-info/WHEEL
arbitrage_tools-0.1.0.dist-info/top_level.txt
arbitrage_tools-0.1.0.dist-info/RECORD
