Metadata-Version: 2.4
Name: arbitrage-tools
Version: 0.1.0
Summary: SOL/USDC Arbitrage
Author: Arbi
License: MIT
Keywords: nfts,arbi,memes,solusdc
Classifier: Programming Language :: Python :: 3
Classifier: License :: OSI Approved :: MIT License
Classifier: Intended Audience :: Developers
Classifier: Typing :: Typed
Requires-Python: >=3.8
License-File: LICENSE
Dynamic: license-file
